[
  {
    "templateName": "SlothMdx",
    "templateDescription": "Astro + MDX - Blog + Podcast Starter",
    "framework": "Astro",
    "cms": "",
    "id": "template-1",
    "author": "Chaikit",
    "authorUrl": "https://github.com/chaikitxyz",
    "imageUrl": "/chaikit.png",
    "previewUrl": "https://example.com/template-1",
    "githubUrl": "https://github.com/chaikitxyz/slothmdx",
    "readmeLink": "https://github.com/chaikitxyz/slothmdx/blob/master/README.md",
    "slug": "slothmdx",
    "usecase": ["Portfolio", "Blog"],
    "css": "CSS",
    "database": "",
    "authentication": "",
    "analytics": ""
  },
  {
    "templateName": "Vue Contentful Template",
    "templateDescription": "This is a Vue template with Contentful CMS integration.",
    "framework": "Vue",
    "cms": "Contentful",
    "id": "template-2",
    "author": "Chaikit",
    "authorUrl": "https://github.com/chaikitxyz",
    "imageUrl": "/chaikit.png",
    "previewUrl": "https://example.com/template-2",
    "githubUrl": "https://github.com/example/template-2",
    "description": "This is a Vue template with Contentful CMS integration.",
    "readmeLink": "https://github.com/chaikitxyz/slothmdx/blob/master/README.md",
    "slug": "vue-contentful-template",
    "usecase": ["Portfolio"],
    "css": "Bootstrap",
    "database": "PostgreSQL",
    "authentication": "Firebase",
    "analytics": "Mixpanel"
  }
]
